shellmind/__init__.py
shellmind/ai_interaction.py
shellmind/cli.py
shellmind/command_executor.py
shellmind/config_manager.py
shellmind/exceptions.py
shellmind/input_processor.py
shellmind/os_adapter.py
shellmindpy-0.0.1.dist-info/licenses/LICENSE
shellmindpy-0.0.1.dist-info/METADATA
shellmindpy-0.0.1.dist-info/WHEEL
shellmindpy-0.0.1.dist-info/top_level.txt
shellmindpy-0.0.1.dist-info/RECORD
