Metadata-Version: 2.4
Name: ShellMindPy
Version: 0.0.1
Summary: AI-Powered Command-Line Assistant
Author-email: Ali Asadi <development@iran.ir>
License-Expression: MIT
Project-URL: Homepage, https://github.com/aliasadi313/ShellMind
Project-URL: Issues, https://github.com/aliasadi313/ShellMind/issues
Classifier: Programming Language :: Python :: 3
Classifier: Operating System :: OS Independent
Requires-Python: >=3.9
License-File: LICENSE
Dynamic: license-file
